kaputt/__init__.py
kaputt-0.0.3.dist-info/DESCRIPTION.rst
kaputt-0.0.3.dist-info/METADATA
kaputt-0.0.3.dist-info/RECORD
kaputt-0.0.3.dist-info/WHEEL
kaputt-0.0.3.dist-info/metadata.json
kaputt-0.0.3.dist-info/top_level.txt
